[{
                "SYGNATURA": 1,
                "PARAFIA": "Barysz",
                "DEKANAT": "Buczacz",
                "TYP": "Księga metrykalna",
                "WSAD": {
                        "FILIACJE": ["od", 1837, "do", 1841],
                        "KOICJE": ["od", 1837, "do", 1841],
                        "ZGONY": ["od", 1837, "do", 1841]
                },
                "JEZYK": ["lat"],
                "LINK": ["http://agadd.home.net.pl/metrykalia/301/sygn.%201/indeks.htm", ""],
                "INFO": "*Porchowa - od 1907 r. samodzielna parafia wyodrębniona z par. Barysz z wsią Zubrzec; **Puźniki - od 1904 r. samodzielna parafia wyodrębniona z par. Barysz; księga przekazana do AGAD z AP - Przemyśl w 1993 r.",
                "MIKROFILM": 73797
        },
        {
                "SYGNATURA": 2,
                "PARAFIA": "Barysz",
                "DEKANAT": "Buczacz",
                "TYP": "Księga metrykalna",
                "WSAD": {
                        "FILIACJE": [1872, 1873, 1875, 1876, 1877, 1878, 1880, 1881, 1882, 1883, 1884, 1885, 1886, 1887, 1888, 1890],
                        "KOICJE": [1872, 1873, 1875, 1876, 1877, 1878, 1880, 1881, 1882, 1883, 1884, 1885, 1886, 1887, 1888, 1890],
                        "ZGONY": [1872, 1873, 1875, 1876, 1877, 1878, 1880, 1881, 1882, 1883, 1884, 1885, 1886, 1887, 1888, 1890]
                },
                "JEZYK": ["lat"],
                "LINK": ["http://agadd.home.net.pl/metrykalia/301/sygn.%202/indeks.htm", ""],
                "INFO": "*, **patrz - sygn. 1; kopie; wpisy urodzeń 1890 (s. 541-549) i zgonów z 1876 r. (s. 175-182) - luzem; rocznik 1874, patrz sygn. 1737; AGAD (zły stan - dalej zs)",
                "MIKROFILM": 73798
        },
        {
                "SYGNATURA": 3,
                "PARAFIA": "Baworów",
                "DEKANAT": "Tarnopol",
                "TYP": "Księga metrykalna",
                "WSAD": {
                        "POSWIADCZENIE": [1830],
                        "FILIACJE": ["od", 1769, "do", 1781]
                },
                "JEZYK": ["lat", "ger"],
                "LINK": ["http://agadd.home.net.pl/metrykalia/301/sygn.%203/indeks.htm", ""],
                "INFO": "wpisy bez rubryk; księga przekazana do AGAD z AP - Przemyśl w 1993 r.",
                "MIKROFILM": 73799
        },
        {
                "SYGNATURA": 4,
                "PARAFIA": "Baworów",
                "DEKANAT": "Tarnopol",
                "TYP": "Księga metrykalna",
                "WSAD": {
                        "FILIACJE": ["od", 1777, "do", 1784]
                },
                "JEZYK": ["lat", "ger"],
                "LINK": ["http://agadd.home.net.pl/metrykalia/301/sygn.%204/indeks.htm", ""],
                "INFO": "księga przekazana do AGAD z AP - Przemyśl w 1993 r.; (zs)",
                "MIKROFILM": 73800
        },
        {
                "SYGNATURA": 5,
                "PARAFIA": "Baworów",
                "DEKANAT": "Tarnopol",
                "TYP": "Księga metrykalna",
                "WSAD": {
                        "FILIACJE": ["od", 1860, "do", 1890]
                },
                "JEZYK": ["lat"],
                "LINK": ["http://agadd.home.net.pl/metrykalia/301/sygn.%205/indeks.htm", ""],
                "INFO": "*od 1909 r. w parafii Sorocko, wyodrębnionej z par. Barysz; w księdze różne dokumenty wszyte i luzem; AGAD",
                "MIKROFILM": 73801
        },
        {
                "SYGNATURA": 6,
                "PARAFIA": "Baworów",
                "DEKANAT": "Tarnopol",
                "TYP": "Księga metrykalna",
                "WSAD": {
                        "FILIACJE": ["od", 1786, "do", 1857]
                },
                "JEZYK": ["lat", "pol", "ger"],
                "LINK": ["http://agadd.home.net.pl/metrykalia/301/sygn.%206/indeks.htm", ""],
                "INFO": "*patrz - sygn. 5; w księdze dokument luzem: nota w sprawie wydania metryki urodzenia, 10 IV 1834 r., składka, s. 69-74; księga przekazana do AGAD z AP - Przemyśl w 1993 r.; (zs)",
                "MIKROFILM": 73802
        },
        {
                "SYGNATURA": 7,
                "PARAFIA": "Baworów",
                "DEKANAT": "Tarnopol",
                "TYP": "Księga metrykalna",
                "WSAD": {
                        "KOICJE": ["od", 1784, "do", 1866]
                },
                "JEZYK": ["lat", "ger"],
                "LINK": ["http://agadd.home.net.pl/metrykalia/301/sygn.%207/indeks.htm", ""],
                "INFO": "*od 1909 r. samodzielna parafia, wyodrębniona z par. Barysz; księga przekazana do AGAD z AP - Przemyśl w 1993 r.",
                "MIKROFILM": 73803
        },
        {
                "SYGNATURA": 8,
                "PARAFIA": "Baworów",
                "DEKANAT": "Tarnopol",
                "TYP": "Księga metrykalna",
                "WSAD": {
                        "ZGONY": ["od", 1784, "do", 1867]
                },
                "JEZYK": ["lat", "ger"],
                "LINK": ["http://agadd.home.net.pl/metrykalia/301/sygn.%208/indeks.htm", ""],
                "INFO": "*patrz - sygn. 8; księga przekazana do AGAD z AP - Przemyśl w 1993 r.",
                "MIKROFILM": 73804
        },
        {
                "SYGNATURA": 9,
                "PARAFIA": "Baworów",
                "DEKANAT": "Tarnopol",
                "TYP": "Księga metrykalna",
                "WSAD": {
                        "KOICJE": ["od", 1777, "do", 1784],
                        "ZGONY": ["od", 1777, "do", 1784]
                },
                "JEZYK": ["lat"],
                "LINK": ["http://agadd.home.net.pl/metrykalia/301/sygn.%209/indeks.htm", ""],
                "INFO": "księga przekazana do AGAD z AP - Przemyśl w 1993 r.",
                "MIKROFILM": 73805
        },
        {
                "SYGNATURA": 10,
                "PARAFIA": "Baworów",
                "DEKANAT": "Tarnopol",
                "TYP": "Księga metrykalna",
                "WSAD": {
                        "KOICJE": ["od", 1784, "do", 1792],
                        "ZGONY": ["od", 1784, "do", 1792]
                },
                "JEZYK": ["lat"],
                "LINK": ["http://agadd.home.net.pl/metrykalia/301/sygn.%2010/indeks.htm", ""],
                "INFO": "księga przekazana do AGAD z AP - Przemyśl w 1993 r.",
                "MIKROFILM": 73806
        },
        {
                "SYGNATURA": 11,
                "PARAFIA": "Baworów",
                "DEKANAT": "Tarnopol",
                "TYP": "Ekstrakty z księgi metrykalnej",
                "WSAD": {
                        "POSWIADCZENIE": [1833],
                        "FILIACJE": [1826, 1828, 1832, 1833],
                        "KOICJE": [1826, 1828, 1832, 1833],
                        "ZGONY": [1826, 1828, 1832, 1833]
                },
                "JEZYK": ["lat"],
                "LINK": ["http://agadd.home.net.pl/metrykalia/301/sygn.%2011/indeks.htm", ""],
                "INFO": "akta (oprawione w księgę) przekazane do AGAD z AP - Przemyśl w 1993 r.",
                "MIKROFILM": 73807
        },
        {
                "SYGNATURA": 12,
                "PARAFIA": "Baworów",
                "DEKANAT": "Tarnopol",
                "TYP": "Księga metrykalna",
                "WSAD": {
                        "FILIACJE": ["od", 1784, "do", 1860],
                        "KOICJE": ["od", 1784, "do", 1892],
                        "ZGONY": ["od", 1784, "do", 1882]
                },
                "JEZYK": ["lat", "pol"],
                "LINK": ["http://agadd.home.net.pl/metrykalia/301/sygn.%2012/indeks.htm", ""],
                "INFO": "*patrz - sygn. 5; przy wpisach dot. urodzeń wszyte dodatkowe dokumenty (wypisy, wyciągi); AGAD; (zs)",
                "MIKROFILM": 73808
        },
        {
                "SYGNATURA": 13,
                "PARAFIA": "Bełz",
                "DEKANAT": "Bełz",
                "TYP": "Ekstrakty z księgi metrykalnej",
                "WSAD": {
                        "POSWIADCZENIE": [1835],
                        "FILIACJE": [1834, 1835],
                        "KOICJE": [1834, 1835],
                        "ZGONY": [1834, 1835]
                },
                "JEZYK": ["lat"],
                "LINK": ["http://agadd.home.net.pl/metrykalia/301/sygn.%2013/indeks.htm", ""],
                "INFO": "niektóre z ww. wsi w przeciągu XIX i XX w. zmieniły swą przynależność parafialną; *Machnówek - od 1912 r. samodzielna parafia wyodrębniona z par. Bełz m. in. z wsiami Staje, Worochta; akta przekazane do AGAD z AP - Przemyśl w 1993 r.",
                "MIKROFILM": 73809
        },
        {
                "SYGNATURA": 14,
                "PARAFIA": "Bełz",
                "DEKANAT": "Bełz",
                "TYP": "Ekstrakty z księgi metrykalnej",
                "WSAD": {
                        "POSWIADCZENIE": [1850],
                        "FILIACJE": [1849, 1850],
                        "KOICJE": [1849, 1850],
                        "ZGONY": [1849, 1850]
                },
                "JEZYK": ["lat"],
                "LINK": ["http://agadd.home.net.pl/metrykalia/301/sygn.%2014/indeks.htm", ""],
                "INFO": "akta przekazane do AGAD z AP - Przemyśl w 1993 r.",
                "MIKROFILM": 73810
        },
        {
                "SYGNATURA": 15,
                "PARAFIA": "Bełz",
                "DEKANAT": "Bełz",
                "TYP": "Ekstrakty z księgi metrykalnej",
                "WSAD": {
                        "POSWIADCZENIE": [1853],
                        "FILIACJE": [1852, 1853],
                        "KOICJE": [1852, 1853],
                        "ZGONY": [1852, 1853]
                },
                "JEZYK": ["lat"],
                "LINK": ["http://agadd.home.net.pl/metrykalia/301/sygn.%2015/indeks.htm", ""],
                "INFO": "akta w kolejności: ur., zg., śl.; przekazane do AGAD z AP - Przemyśl w 1993 r.",
                "MIKROFILM": 73811
        },
        {
                "SYGNATURA": 16,
                "PARAFIA": "Białogóra (Weisenberg)",
                "DEKANAT": "Gródek Jagielloński",
                "TYP": "Księga metrykalna",
                "WSAD": {
                        "FILIACJE": ["od", 1786, "do", 1826]
                },
                "JEZYK": ["lat", "ger"],
                "LINK": ["http://agadd.home.net.pl/metrykalia/301/sygn.%2016/indeks.htm", ""],
                "INFO": "*księga zawiera dwa tomy wpisów: I. 1788-1825, s. 1-96; II. 1786-1826, s. 97-189; przekazana do AGAD z AP - Przemyśl w 1993 r.",
                "MIKROFILM": 73812
        },
        {
                "SYGNATURA": 17,
                "PARAFIA": "Białogóra (Weisenberg)",
                "DEKANAT": "Gródek Jagielloński",
                "TYP": "Księga metrykalna",
                "WSAD": {
                        "FILIACJE": ["od", 1826, "do", 1838]
                },
                "JEZYK": ["lat"],
                "LINK": ["http://agadd.home.net.pl/metrykalia/301/sygn.%2017/indeks.htm", ""],
                "INFO": "na końcu księgi wszyty spis osób urodzonych w parafii Białogóra, nie obejmujący wszystkich lat, s. 95-96 (wpisy wg dawnej, zachowanej paginacji w księdze); księga przekazana do AGAD z AP - Przemyśl w 1993 r.",
                "MIKROFILM": 73813
        },
        {
                "SYGNATURA": 18,
                "PARAFIA": "Białogóra (Weisenberg)",
                "DEKANAT": "Gródek Jagielloński",
                "TYP": "Księga metrykalna",
                "WSAD": {
                        "FILIACJE": ["od", 1838, "do", 1865]
                },
                "JEZYK": ["lat", "ger"],
                "LINK": ["http://agadd.home.net.pl/metrykalia/301/sygn.%2018/indeks.htm", ""],
                "INFO": "AGAD",
                "MIKROFILM": 73814
        },
        {
                "SYGNATURA": 19,
                "PARAFIA": "Białogóra (Weisenberg)",
                "DEKANAT": "Gródek Jagielloński",
                "TYP": "Księga metrykalna",
                "WSAD": {
                        "KOICJE": ["od", 1786, "do", 1837]
                },
                "JEZYK": ["lat", "pol", "ger"],
                "LINK": ["http://agadd.home.net.pl/metrykalia/301/sygn.%2019/indeks.htm", ""],
                "INFO": "t. I; na końcu księgi wszyty spis osób wstępujących w związek małżeński w parafii Białogóra, nie obejmujący wszystkich lat, s. 65-66 (wpisy wg dawnej, zachowanej paginacji w księdze); księga przekazana do AGAD z AP - Przemyśl w 1993 r.",
                "MIKROFILM": 73815
        },
        {
                "SYGNATURA": 20,
                "PARAFIA": "Białogóra (Weisenberg)",
                "DEKANAT": "Gródek Jagielloński",
                "TYP": "Księga metrykalna",
                "WSAD": {
                        "KOICJE": ["od", 1787, "do", 1861]
                },
                "JEZYK": ["lat", "pol", "ger"],
                "LINK": ["http://agadd.home.net.pl/metrykalia/301/sygn.%2020/indeks.htm", ""],
                "INFO": "t. I; na końcu księgi wszyty spis osób wstępujących w związek małżeński w parafii Białogóra, nie obejmujący wszystkich lat, s. 101 (wpisy wg dawnej, zachowanej paginacji w księdze); księga przekazana do AGAD z AP - Przemyśl w 1993 r.",
                "MIKROFILM": 73816
        },
        {
                "SYGNATURA": 21,
                "PARAFIA": "Białogóra (Weisenberg)",
                "DEKANAT": "Gródek Jagielloński",
                "TYP": "Księga metrykalna",
                "WSAD": {
                        "KOICJE": ["od", 1861, "do", 1887]
                },
                "JEZYK": ["lat", "pol"],
                "LINK": ["http://agadd.home.net.pl/metrykalia/301/sygn.%2021/indeks.htm", ""],
                "INFO": "t. II; z 1887 r. - 1 wpis; AGAD",
                "MIKROFILM": 73817
        },
        {
                "SYGNATURA": 22,
                "PARAFIA": "Białogóra (Weisenberg)",
                "DEKANAT": "Gródek Jagielloński",
                "TYP": "Księga metrykalna",
                "WSAD": {
                        "ZGONY": ["od", 1776, "do", 1859]
                },
                "JEZYK": ["lat", "pol", "ger"],
                "LINK": ["http://agadd.home.net.pl/metrykalia/301/sygn.%2022/indeks.htm", ""],
                "INFO": "t. I; księga przekazana do AGAD z AP - Przemyśl w 1993 r.",
                "MIKROFILM": 73818
        },
        {
                "SYGNATURA": 23,
                "PARAFIA": "Białogóra (Weisenberg)",
                "DEKANAT": "Gródek Jagielloński",
                "TYP": "Księga metrykalna",
                "WSAD": {
                        "ZGONY": ["od", 1786, "do", 1839]
                },
                "JEZYK": ["lat", "pol", "ger"],
                "LINK": ["http://agadd.home.net.pl/metrykalia/301/sygn.%2023/indeks.htm", ""],
                "INFO": "t. II; w księdze spis zmarłych, nie obejmujący wszystkich lat, s. 105-106; księga przekazana do AGAD z AP - Przemyśl w 1993 r.",
                "MIKROFILM": 73819
        },
        {
                "SYGNATURA": 24,
                "PARAFIA": "Białogóra (Weisenberg)",
                "DEKANAT": "Gródek Jagielloński",
                "TYP": "Księga metrykalna",
                "WSAD": {
                        "ZGONY": ["od", 1860, "do", 1889]
                },
                "JEZYK": ["lat", "ger"],
                "LINK": ["http://agadd.home.net.pl/metrykalia/301/sygn.%2024/indeks.htm", ""],
                "INFO": "t. II; AGAD",
                "MIKROFILM": 73820
        },
        {
                "SYGNATURA": 25,
                "PARAFIA": "Białogóra (Weisenberg)",
                "DEKANAT": "Gródek Jagielloński",
                "TYP": "Ekstrakty z księgi metrykalnej",
                "WSAD": {
                        "FILIACJE": [1818, 1823],
                        "KOICJE": [1818, 1823],
                        "ZGONY": [1818, 1823]
                },
                "JEZYK": ["lat", "ger"],
                "LINK": ["http://agadd.home.net.pl/metrykalia/301/sygn.%2025/indeks.htm", ""],
                "INFO": "dwie składki przekazane do AGAD z AP - Przemyśl w 1993 r.; (bardzo zły stan - dalej bzs)",
                "MIKROFILM": 73821
        },
        {
                "SYGNATURA": 26,
                "PARAFIA": "Biały Kamień",
                "DEKANAT": "Złoczów",
                "TYP": "Księga metrykalna",
                "WSAD": {
                        "FILIACJE": ["od", 1665, "do", 1777]
                },
                "JEZYK": ["lat"],
                "LINK": ["http://agadd.home.net.pl/metrykalia/301/sygn.%2026/indeks.htm", ""],
                "INFO": "wpisy bez rubryk; księga przekazana do AGAD z AP - Przemyśl w 1993 r. ; (zs)",
                "MIKROFILM": 73822
        },
        {
                "SYGNATURA": 27,
                "PARAFIA": "Biały Kamień",
                "DEKANAT": "Złoczów",
                "TYP": "Księga metrykalna",
                "WSAD": {
                        "FILIACJE": ["od", 1665, "do", 1746]
                },
                "JEZYK": ["lat"],
                "LINK": ["http://agadd.home.net.pl/metrykalia/301/sygn.%2027/indeks.htm", ""],
                "INFO": "wpisy bez rubryk, do 1670 r. całkowicie nieczytelne; księga przekazana do AGAD z AP - Przemyśl w 1993 r.",
                "MIKROFILM": 73823
        },
        {
                "SYGNATURA": 28,
                "PARAFIA": "Biały Kamień",
                "DEKANAT": "Złoczów",
                "TYP": "Księga metrykalna",
                "WSAD": {
                        "FILIACJE": ["od", 1784, "do", 1834]
                },
                "JEZYK": ["lat", "ger"],
                "LINK": ["http://agadd.home.net.pl/metrykalia/301/sygn.%2028/indeks.htm", ""],
                "INFO": "t. I; księga przekazana do AGAD z AP - Przemyśl w 1993 r.",
                "MIKROFILM": 73824
        },
        {
                "SYGNATURA": 29,
                "PARAFIA": "Biały Kamień",
                "DEKANAT": "Złoczów",
                "TYP": "Księga metrykalna",
                "WSAD": {
                        "FILIACJE": ["od", 1834, "do", 1862]
                },
                "JEZYK": ["lat"],
                "LINK": ["http://agadd.home.net.pl/metrykalia/301/sygn.%2029/indeks.htm", ""],
                "INFO": "t. II; księga przekazana do AGAD z AP - Przemyśl w 1993 r.",
                "MIKROFILM": 73825
        },
        {
                "SYGNATURA": 30,
                "PARAFIA": "Biały Kamień",
                "DEKANAT": "Złoczów",
                "TYP": "Księga metrykalna",
                "WSAD": {
                        "KOICJE": ["od", 1784, "do", 1845]
                },
                "JEZYK": ["lat", "ger"],
                "LINK": ["http://agadd.home.net.pl/metrykalia/301/sygn.%2030/indeks.htm", ""],
                "INFO": "t. I; księga przekazana do AGAD z AP - Przemyśl w 1993 r.",
                "MIKROFILM": 73826
        },
        {
                "SYGNATURA": 31,
                "PARAFIA": "Biały Kamień",
                "DEKANAT": "Złoczów",
                "TYP": "Księga metrykalna",
                "WSAD": {
                        "ZGONY": ["od", 1750, "do", 1782]
                },
                "JEZYK": ["lat"],
                "LINK": ["http://agadd.home.net.pl/metrykalia/301/sygn.%2031/indeks.htm", ""],
                "INFO": "księga przekazana do AGAD z AP - Przemyśl w 1993 r.",
                "MIKROFILM": 73827
        },
        {
                "SYGNATURA": 32,
                "PARAFIA": "Biały Kamień",
                "DEKANAT": "Złoczów",
                "TYP": "Księga metrykalna",
                "WSAD": {
                        "ZGONY": ["od", 1784, "do", 1835]
                },
                "JEZYK": ["lat", "pol"],
                "LINK": ["http://agadd.home.net.pl/metrykalia/301/sygn.%2032/indeks.htm", ""],
                "INFO": "t. I; księga przekazana do AGAD z AP - Przemyśl w 1993 r.",
                "MIKROFILM": 73828
        },
        {
                "SYGNATURA": 33,
                "PARAFIA": "Biały Kamień",
                "DEKANAT": "Złoczów",
                "TYP": "Księga metrykalna",
                "WSAD": {
                        "FILIACJE": ["od", 1748, "do", 1778],
                        "KOICJE": ["od", 1748, "do", 1750]
                },
                "JEZYK": ["lat"],
                "LINK": ["http://agadd.home.net.pl/metrykalia/301/sygn.%2033/indeks.htm", ""],
                "INFO": "wpisy bez rubryk; księga prowadzona dwustronnie i tak spaginowana (po obrocie): ks. ur., s. 1-357, ks. śl., s. 358-362; ozdobna bordiura rozpoczynająca każdą serię wpisów; księga przekazana do AGAD z AP - Przemyśl w 1993 r.",
                "MIKROFILM": 73829
        },
        {
                "SYGNATURA": 34,
                "PARAFIA": "Biały Kamień",
                "DEKANAT": "Złoczów",
                "TYP": "Ekstrakty z księgi metrykalnej",
                "WSAD": {
                        "FILIACJE": [1831],
                        "KOICJE": [1831],
                        "ZGONY": [1831]
                },
                "JEZYK": ["lat"],
                "LINK": ["http://agadd.home.net.pl/metrykalia/301/sygn.%2034/indeks.htm", ""],
                "INFO": "akta przekazane do AGAD z AP - Przemyśl w 1993 r.",
                "MIKROFILM": 73830
        },
        {
                "SYGNATURA": 35,
                "PARAFIA": "Biłka Szlachecka",
                "DEKANAT": "Lwów",
                "WSAD": {
                        "FILIACJE": ["od", 1822, "do", 1847]
                },
                "JEZYK": ["lat", "ger"],
                "LINK": ["http://agadd.home.net.pl/metrykalia/301/sygn.%2035/indeks.htm", ""],
                "INFO": "księga przekazana do AGAD z AP - Przemyśl w 1993 r.",
                "MIKROFILM": 73831
        },
        {
                "SYGNATURA": 36,
                "PARAFIA": "Biłka Szlachecka",
                "DEKANAT": "Lwów",
                "TYP": "Księga metrykalna",
                "WSAD": {
                        "FILIACJE": ["od", 1831, "do", 1857]
                },
                "JEZYK": ["lat", "ger"],
                "LINK": ["http://agadd.home.net.pl/metrykalia/301/sygn.%2036/indeks.htm", ""],
                "INFO": "*od 76 s. obowiązuje współczesna paginacja; księga przekazana do AGAD z AP - Przemyśl w 1993 r.",
                "MIKROFILM": 73832
        },
        {
                "SYGNATURA": 37,
                "PARAFIA": "Biłka Szlachecka",
                "DEKANAT": "Lwów",
                "WSAD": {
                        "KOICJE": ["od", 1678, "do", 1772]
                },
                "JEZYK": ["lat"],
                "LINK": ["http://agadd.home.net.pl/metrykalia/301/sygn.%2037/indeks.htm", ""],
                "INFO": "wpisy bez rubryk; *z 1772 r. - 1 wpis; księga przekazana do AGAD z AP - Przemyśl w 1993 r.",
                "MIKROFILM": 73833
        },
        {
                "SYGNATURA": 38,
                "PARAFIA": "Biłka Szlachecka",
                "DEKANAT": "Lwów",
                "TYP": "Księga metrykalna",
                "WSAD": {
                        "KOICJE": ["od", 1765, "do", 1775, "od", 1788, "do", 1822, "od", 1822, "do", 1829]
                },
                "JEZYK": ["lat", "pol"],
                "LINK": ["http://agadd.home.net.pl/metrykalia/301/sygn.%2038/indeks.htm", ""],
                "INFO": "wpisy częściowo w rubrykach; *właściwe wpisy ślubów z lat 1765-1775, ponadto księga zawiera wpisy zapowiedzi z lat 1788-1822, s. 61-127 oraz wykaz mszy odprawionych w parafii w latach 1822-1829, s. 128-173; przekazana do AGAD z AP - Przemyśl w 1993 r.",
                "MIKROFILM": 73834
        },
        {
                "SYGNATURA": 39,
                "PARAFIA": "Biłka Szlachecka",
                "DEKANAT": "Lwów",
                "TYP": "Księga metrykalna",
                "WSAD": {
                        "KOICJE": ["od", 1785, "do", 1788]
                },
                "JEZYK": ["lat", "pol"],
                "LINK": ["http://agadd.home.net.pl/metrykalia/301/sygn.%2039/indeks.htm", ""],
                "INFO": "księga przekazana do AGAD z AP - Przemyśl w 1993 r.",
                "MIKROFILM": 73835
        },
        {
                "SYGNATURA": 40,
                "PARAFIA": "Biłka Szlachecka",
                "DEKANAT": "Lwów",
                "TYP": "Księga metrykalna",
                "WSAD": {
                        "FILIACJE": ["od", 1785, "do", 1836],
                        "ZGONY": ["od", 1785, "do", 1836]
                },
                "JEZYK": ["lat", "pol", "ger"],
                "LINK": ["http://agadd.home.net.pl/metrykalia/301/sygn.%2040/indeks.htm", ""],
                "INFO": "t. XII; *od s. 217 obowiązuje współczesna paginacja; księga przekazana do AGAD z AP - Przemyśl w 1993 r.",
                "MIKROFILM": 73836
        },
        {
                "SYGNATURA": 41,
                "PARAFIA": "Biłka Szlachecka",
                "DEKANAT": "Lwów",
                "TYP": "Księga metrykalna",
                "WSAD": {
                        "KOICJE": ["od", 1739, "do", 1774],
                        "ZGONY": ["od", 1739, "do", 1774]
                },
                "JEZYK": ["lat", "pol"],
                "LINK": ["http://agadd.home.net.pl/metrykalia/301/sygn.%2041/indeks.htm", ""],
                "INFO": "wpisy bez rubryk; księga zawiera inne zapiski nie związane z wpisami metrykalnymi: &quot;Ad perpetuam rei memoriam&quot;, s. 118, &quot;Fundacje i zapisy kościoła biłeckiego&quot;, s. 119-120, &quot;Obligacje kościelne&quot;, s. 120, &quot;kwerenda papierów fundacyjnych do kościoła biłeckiego należących w księgach konsystorskich lwowskich&quot; z lat 1546-1697, s. 120-121 oraz &quot;Documenta ad ecclesiam biłcensem&quot; (dokument z 1441 r. oraz fr. dokumentu z 1454 r.) wpisane do księgi przez proboszcza w 1762 r., s. 122; księga przekazana do AGAD z AP - Przemyśl w 1993 r.",
                "MIKROFILM": 73837
        },
        {
                "SYGNATURA": 42,
                "PARAFIA": "Biłka Szlachecka",
                "DEKANAT": "Lwów",
                "TYP": "Księga metrykalna",
                "WSAD": {
                        "KOICJE": ["od", 1785, "do", 1821],
                        "ZGONY": ["od", 1785, "do", 1848]
                },
                "JEZYK": ["lat", "pol", "ger"],
                "LINK": ["http://agadd.home.net.pl/metrykalia/301/sygn.%2042/indeks.htm", ""],
                "INFO": "t. XV; księga przekazana do AGAD z AP - Przemyśl w 1993 r.",
                "MIKROFILM": 73838
        },
        {
                "SYGNATURA": 43,
                "PARAFIA": "Biłka Szlachecka",
                "DEKANAT": "Lwów",
                "TYP": "Księga metrykalna",
                "WSAD": {
                        "FILIACJE": ["od", 1787, "do", 1797],
                        "KOICJE": ["od", 1787, "do", 1836],
                        "ZGONY": ["od", 1785, "do", 1810]
                },
                "JEZYK": ["lat", "pol", "ger"],
                "LINK": ["http://agadd.home.net.pl/metrykalia/301/sygn.%2043/indeks.htm", ""],
                "INFO": "t. XI; księga przekazana do AGAD z AP - Przemyśl w 1993 r.",
                "MIKROFILM": 73839
        },
        {
                "SYGNATURA": 44,
                "PARAFIA": "Biłka Szlachecka",
                "DEKANAT": "Lwów",
                "TYP": "Ekstrakty z księgi metrykalnej",
                "WSAD": {
                        "POSWIADCZENIE": [1833, 1834],
                        "FILIACJE": [1833],
                        "KOICJE": [1833, 1861],
                        "ZGONY": [1833, 1861]
                },
                "JEZYK": ["lat"],
                "LINK": ["http://agadd.home.net.pl/metrykalia/301/sygn.%2044/indeks.htm", ""],
                "INFO": "5 składek; akta przekazane do AGAD z AP - Przemyśl w 1993 r.",
                "MIKROFILM": 73840
        },
        {
                "SYGNATURA": 45,
                "PARAFIA": "Bohorodczany",
                "DEKANAT": "Stanisławów",
                "TYP": "Księga metrykalna",
                "WSAD": {
                        "FILIACJE": ["od", 1784, "do", 1827]
                },
                "JEZYK": ["lat", "pol"],
                "LINK": ["http://agadd.home.net.pl/metrykalia/301/sygn.%2045/indeks.htm", ""],
                "INFO": "t. I; , dodatkowe wpisy dla wsi Grabowiec z lat: 1812, 1824, 1827, s. 173; księga przekazana do AGAD z AP - Przemyśl w 1993 r.",
                "MIKROFILM": 73841
        },
        {
                "SYGNATURA": 46,
                "PARAFIA": "Bohorodczany",
                "DEKANAT": "Stanisławów",
                "TYP": "Księga metrykalna",
                "WSAD": {
                        "KOICJE": ["od", 1784, "do", 1860]
                },
                "JEZYK": ["lat", "pol"],
                "LINK": ["http://agadd.home.net.pl/metrykalia/301/sygn.%2046/indeks.htm", ""],
                "INFO": "w księdze bifolium luzem: świadectwo ślubu, wyst. 7 X 1807 r., s. 173; księga przekazana do AGAD z AP - Przemyśl w 1993 r.",
                "MIKROFILM": 73842
        },
        {
                "SYGNATURA": 47,
                "PARAFIA": "Bohorodczany",
                "DEKANAT": "Stanisławów",
                "TYP": "Księga metrykalna",
                "WSAD": {
                        "ZGONY": ["od", 1784, "do", 1850]
                },
                "JEZYK": ["lat", "pol"],
                "LINK": ["http://agadd.home.net.pl/metrykalia/301/sygn.%2047/indeks.htm", ""],
                "INFO": "t. II; księga przekazana do AGAD z AP - Przemyśl w 1993 r.",
                "MIKROFILM": 73843
        },
        {
                "SYGNATURA": 48,
                "PARAFIA": "Bohorodczany",
                "DEKANAT": "Stanisławów",
                "TYP": "Księga metrykalna",
                "WSAD": {
                        "FILIACJE": ["od", 1715, "do", 1754],
                        "KOICJE": ["od", 1715, "do", 1754]
                },
                "JEZYK": ["lat"],
                "LINK": ["http://agadd.home.net.pl/metrykalia/301/sygn.%2048/indeks.htm", ""],
                "INFO": "wpisy bez rubryk, księga prowadzona dwustronnie: wpisy ur., s. 1-97, wpisy śl, s. 98-122; ozdobna bordiura rozpoczynająca każdą serię wpisów; księga przekazana do AGAD z AP - Przemyśl w 1993 r.",
                "MIKROFILM": 73844
        },
        {
                "SYGNATURA": 49,
                "PARAFIA": "Bohorodczany",
                "DEKANAT": "Stanisławów",
                "TYP": "Ekstrakty z księgi metrykalnej",
                "WSAD": {
                        "POSWIADCZENIE": [1838, 1843],
                        "FILIACJE": [1837, 1838, 1841, 1843, 1844, 1853],
                        "KOICJE": [1837, 1838, 1841, 1843, 1844, 1853],
                        "ZGONY": [1837, 1838, 1841, 1843, 1844, 1853]
                },
                "JEZYK": ["lat"],
                "LINK": ["http://agadd.home.net.pl/metrykalia/301/sygn.%2049/indeks.htm", ""],
                "INFO": "plik składek i luźnych kart; akta przekazane do AGAD z AP - Przemyśl w 1993 r.",
                "MIKROFILM": 73845
        },
        {
                "SYGNATURA": 50,
                "PARAFIA": "Bojan",
                "DEKANAT": "Czerniowce",
                "TYP": "Księga metrykalna",
                "WSAD": {
                        "FILIACJE": ["od", 1828, "do", 1877]
                },
                "JEZYK": ["lat", "pol", "ger"],
                "LINK": ["http://agadd.home.net.pl/metrykalia/301/sygn.%2050/indeks.htm", ""],
                "INFO": "t. I-VI; w księdze akta luzem: korespondencja, wypisy z akt ur., s. 147-148; AGAD; (zs)",
                "MIKROFILM": 73846
        },
        {
                "SYGNATURA": 51,
                "PARAFIA": "Bojan",
                "DEKANAT": "Czerniowce",
                "TYP": "Księga metrykalna",
                "WSAD": {
                        "ZGONY": ["od", 1828, "do", 1877]
                },
                "JEZYK": ["lat"],
                "LINK": ["http://agadd.home.net.pl/metrykalia/301/sygn.%2051/indeks.htm", ""],
                "INFO": "t. II, IV, VI; w księdze potwierdzenie odbioru ksiąg metrykalnych z parafii Bojan przez proboszcza par. w Niedźwiedniku (dolnośląskie), 3 X 1948 r., luzem, s. 79; AGAD; (zs)",
                "MIKROFILM": 73847
        },
        {
                "SYGNATURA": 52,
                "PARAFIA": "Bojan",
                "DEKANAT": "Czerniowce",
                "TYP": "Księga metrykalna",
                "WSAD": {
                        "FILIACJE": ["od", 1782, "do", 1874],
                        "KOICJE": ["od", 1782, "do", 1873]
                },
                "JEZYK": ["lat"],
                "LINK": ["http://agadd.home.net.pl/metrykalia/301/sygn.%2052/indeks.htm", ""],
                "INFO": "t.: I, III, V; wpisy ur., s. 59-228, wpisy śl., s. 1-58; w księdze dokumenty luzem (korespondencja, wyciągi z akt metrykalnych), s. 226-228; AGAD; (bzs)",
                "MIKROFILM": 73848
        },
        {
                "SYGNATURA": 53,
                "PARAFIA": "Bojan",
                "DEKANAT": "Czerniowce",
                "TYP": "Indeks alfabetyczny",
                "WSAD": {
                        "FILIACJE": ["od", 1783, "do", 1944]
                },
                "JEZYK": ["lat"],
                "LINK": ["http://agadd.home.net.pl/metrykalia/301/sygn.%2053/indeks.htm", ""],
                "INFO": "NIE FILIACJE - TYLKO INDEKS, w księdze bifolium luzem - dodatkowe wpisy indeksowe z lat 1936-1941, s. 82-85; AGAD",
                "MIKROFILM": 73849
        },
        {
                "SYGNATURA": 54,
                "PARAFIA": "Bojan",
                "DEKANAT": "Czerniowce",
                "TYP": "Indeks alfabetyczny",
                "WSAD": {
                        "ZGONY": ["od", 1804, "do", 1943]
                },
                "JEZYK": ["lat", "rum"],
                "LINK": ["http://agadd.home.net.pl/metrykalia/301/sygn.%2054/indeks.htm", ""],
                "INFO": "dołączony wyciąg z aktu zgonu, wyst. 31 III 1837 r., j. rum., s. 49-50; AGAD",
                "MIKROFILM": 73850
        },
        {
                "SYGNATURA": 55,
                "PARAFIA": "Bolechów",
                "DEKANAT": "Dolina",
                "TYP": "Ekstrakty z księgi metrykalnej",
                "WSAD": {
                        "POSWIADCZENIE": [1840],
                        "FILIACJE": ["od", 1839, "do", 1940]
                },
                "JEZYK": ["lat"],
                "LINK": ["http://agadd.home.net.pl/metrykalia/301/sygn.%2055/indeks.htm", ""],
                "INFO": "akta przekazane do AGAD z AP - Przemyśl w 1993 r.",
                "MIKROFILM": 73851
        },
        {
                "SYGNATURA": 56,
                "PARAFIA": "Bolechów",
                "DEKANAT": "Dolina",
                "TYP": "Księga metrykalna",
                "WSAD": {
                        "POSWIADCZENIE": [1832],
                        "FILIACJE": ["od", 1608, "do", 1694],
                        "KOICJE": ["od", 1608, "do", 1694]
                },
                "JEZYK": ["lat"],
                "LINK": ["http://agadd.home.net.pl/metrykalia/301/sygn.%2056/indeks.htm", ""],
                "INFO": "wpisy bez rubryk: chrzty str. 1-134, śluby str.135-188; po konserwacji; niektóre wpisy nieczytelne; akta przekazane do AGAD z AP - Przemyśl w 1993 r.",
                "MIKROFILM": 73852
        },
        {
                "SYGNATURA": 57,
                "PARAFIA": "Bolechów",
                "DEKANAT": "Dolina",
                "TYP": "Księga metrykalna",
                "WSAD": {
                        "KOICJE": ["od", 1776, "do", 1784],
                        "ZGONY": ["od", 1776, "do", 1784]
                },
                "JEZYK": ["lat"],
                "LINK": ["http://agadd.home.net.pl/metrykalia/301/sygn.%2057/indeks.htm", ""],
                "INFO": "*wpisy w księdze przemieszane z innymi zapiskami, częściowo nieczytelne; prawdopodobnie księga został wykorzystana do innych celów, zapiski dotyczą przebiegu sprawy sądowej; księga prowadzona dwustronnie; przekazana do AGAD z AP - Przemyśl w 1993 r.",
                "MIKROFILM": 73853
        },
        {
                "SYGNATURA": 58,
                "PARAFIA": "Bolechów",
                "DEKANAT": "Dolina",
                "TYP": "Ekstrakty z księgi metrykalnej",
                "WSAD": {
                        "POSWIADCZENIE": [1825],
                        "FILIACJE": [1823, 1825],
                        "KOICJE": [1823, 1825],
                        "ZGONY": [1823, 1825]
                },
                "JEZYK": ["lat"],
                "LINK": ["http://agadd.home.net.pl/metrykalia/301/sygn.%2058/indeks.htm", ""],
                "INFO": "akta przekazane do AGAD z AP - Przemyśl w 1993 r.",
                "MIKROFILM": 73854
        },
        {
                "SYGNATURA": 59,
                "PARAFIA": "Bolechów",
                "DEKANAT": "Dolina",
                "TYP": "Ekstrakty z księgi metrykalnej",
                "WSAD": {
                        "POSWIADCZENIE": [1825],
                        "FILIACJE": [1825],
                        "KOICJE": [1825],
                        "ZGONY": [1825]
                },
                "JEZYK": ["lat"],
                "LINK": ["http://agadd.home.net.pl/metrykalia/301/sygn.%2059/indeks.htm", ""],
                "INFO": "akta przekazane do AGAD z AP - Przemyśl w 1993 r.",
                "MIKROFILM": 73855
        },
        {
                "SYGNATURA": 60,
                "PARAFIA": "Bolechów",
                "DEKANAT": "Dolina",
                "TYP": "Ekstrakty z księgi metrykalnej",
                "WSAD": {
                        "POSWIADCZENIE": [1827],
                        "FILIACJE": [1826, 1827],
                        "KOICJE": [1826, 1827],
                        "ZGONY": [1826, 1827]
                },
                "JEZYK": ["lat"],
                "LINK": ["http://agadd.home.net.pl/metrykalia/301/sygn.%2060/indeks.htm", ""],
                "INFO": "akta przekazane do AGAD z AP - Przemyśl w 1993 r.",
                "MIKROFILM": 73856
        },
        {
                "SYGNATURA": 61,
                "PARAFIA": "Bolechów",
                "DEKANAT": "Dolina",
                "TYP": "Ekstrakty z księgi metrykalnej",
                "WSAD": {
                        "POSWIADCZENIE": [1828],
                        "FILIACJE": [1827, 1828],
                        "KOICJE": [1827, 1828],
                        "ZGONY": [1827, 1828]
                },
                "JEZYK": ["lat"],
                "LINK": ["http://agadd.home.net.pl/metrykalia/301/sygn.%2061/indeks.htm", ""],
                "INFO": "akta przekazane do AGAD z AP - Przemyśl w 1993 r.",
                "MIKROFILM": 73857
        },
        {
                "SYGNATURA": 62,
                "PARAFIA": "Bolechów",
                "DEKANAT": "Dolina",
                "TYP": "Ekstrakty z księgi metrykalnej",
                "WSAD": {
                        "FILIACJE": [1834],
                        "KOICJE": [1834],
                        "ZGONY": [1834]
                },
                "JEZYK": ["lat"],
                "LINK": ["http://agadd.home.net.pl/metrykalia/301/sygn.%2062/indeks.htm", ""],
                "INFO": "akta przekazane do AGAD z AP - Przemyśl w 1993 r.",
                "MIKROFILM": 73858
        },
        {
                "SYGNATURA": 63,
                "PARAFIA": "Bołszowce",
                "DEKANAT": "Kąkolniki",
                "TYP": "Księga metrykalna",
                "WSAD": {
                        "FILIACJE": ["od", 1793, "do", 1818]
                },
                "JEZYK": ["lat",
                        "pol"
                ],
                "LINK": ["http://agadd.home.net.pl/metrykalia/301/sygn.%2063/indeks.htm", ""],
                "INFO": "t. I; księga przekazana do AGAD z AP - Przemyśl w 1993 r.; (bzs)",
                "MIKROFILM": 73858
        },
        {
                "SYGNATURA": 64,
                "PARAFIA": "Borszczów",
                "DEKANAT": "Borszczów",
                "TYP": "Księga metrykalna",
                "WSAD": {
                        "FILIACJE": ["od", 1769, "do", 1785, 1794, 1800, 1802]
                },
                "JEZYK": ["lat",
                        "pol"
                ],
                "LINK": ["http://agadd.home.net.pl/metrykalia/301/sygn.%2064/indeks.htm", ""],
                "INFO": "wpisy bez rubryk; *w księdze także odręczne notatki dotyczące wydatków kościelnych, śluby i przyrzeczenia parafian m. in. z lat 1794, 1800, 1802, s. 139-150; księga przekazana do AGAD z AP - Przemyśl w 1993 r.; (zs)",
                "MIKROFILM": 73860
        },
        {
                "SYGNATURA": 65,
                "PARAFIA": "Borszczów",
                "DEKANAT": "Borszczów",
                "TYP": "Księga metrykalna",
                "WSAD": {
                        "POSWIADCZENIE": [1818],
                        "FILIACJE": ["od", 1743, "do", 1769, 1818]
                },
                "JEZYK": ["lat"],
                "LINK": ["http://agadd.home.net.pl/metrykalia/301/sygn.%2065/indeks.htm", ""],
                "INFO": "wpisy bez rubryk; księga przekazana do AGAD z AP - Przemyśl w 1993 r.",
                "MIKROFILM": 73861
        },
        {
                "SYGNATURA": 66,
                "PARAFIA": "Borszczów",
                "DEKANAT": "Borszczów",
                "TYP": "Księga metrykalna",
                "WSAD": {
                        "FILIACJE": ["od", 1818, "do", 1835]
                },
                "JEZYK": ["lat",
                        "pol",
                        "ger"
                ],
                "LINK": ["http://agadd.home.net.pl/metrykalia/301/sygn.%2066/indeks.htm", ""],
                "INFO": "AGAD",
                "MIKROFILM": 73862
        },
        {
                "SYGNATURA": 67,
                "PARAFIA": "Borszczów",
                "DEKANAT": "Borszczów",
                "TYP": "Księga metrykalna",
                "WSAD": {
                        "FILIACJE": ["od", 1842, "do", 1869]
                },
                "JEZYK": ["lat",
                        "ger"
                ],
                "LINK": ["http://agadd.home.net.pl/metrykalia/301/sygn.%2067/indeks.htm", ""],
                "INFO": "AGAD",
                "MIKROFILM": 73863
        },
        {
                "SYGNATURA": 68,
                "PARAFIA": "Borszczów",
                "DEKANAT": "Borszczów",
                "TYP": "Księga metrykalna",
                "WSAD": {
                        "FILIACJE": ["od", 1872, "do", 1885]
                },
                "JEZYK": ["lat"],
                "LINK": ["http://agadd.home.net.pl/metrykalia/301/sygn.%2068/indeks.htm", ""],
                "INFO": "kopie; AGAD; (zs)",
                "MIKROFILM": 73864
        },
        {
                "SYGNATURA": 69,
                "PARAFIA": "Borszczów",
                "DEKANAT": "Borszczów",
                "TYP": "Księga metrykalna",
                "WSAD": {
                        "FILIACJE": ["od", 1827, "do", 1885]
                },
                "JEZYK": ["lat",
                        "ger"
                ],
                "LINK": ["http://agadd.home.net.pl/metrykalia/301/sygn.%2069/indeks.htm", ""],
                "INFO": "AGAD",
                "MIKROFILM": 73865
        },
        {
                "SYGNATURA": 70,
                "PARAFIA": "Borszczów",
                "DEKANAT": "Borszczów",
                "TYP": "Księga metrykalna",
                "WSAD": {
                        "FILIACJE": ["od", 1837, "do", 1866]
                },
                "JEZYK": ["lat",
                        "ger"
                ],
                "LINK": ["http://agadd.home.net.pl/metrykalia/301/sygn.%2070/indeks.htm", ""],
                "INFO": "AGAD",
                "MIKROFILM": 73866
        },
        {
                "SYGNATURA": 71,
                "PARAFIA": "Borszczów",
                "DEKANAT": "Borszczów",
                "TYP": "Księga metrykalna",
                "WSAD": {
                        "KOICJE": ["od", 1769, "do", 1784, 1799]
                },
                "JEZYK": ["lat",
                        "pol"
                ],
                "LINK": ["http://agadd.home.net.pl/metrykalia/301/sygn.%2071/indeks.htm", ""],
                "INFO": "wpisy bez rubryk; w księdze także inne zapiski, m. in.: status animarum sporządzony w 1799 r. (wiz. 1804), s. 46-119, kazanie wiekowe na koniec 1800 r. , s. 126 oraz kazanie do pobożnych parafian, s. 130; księga przekazana do AGAD z AP - Przmyśl w 1993 r.",
                "MIKROFILM": 73867
        },
        {
                "SYGNATURA": 72,
                "PARAFIA": "Borszczów",
                "DEKANAT": "Borszczów",
                "TYP": "Księga metrykalna",
                "WSAD": {
                        "KOICJE": ["od", 1847, "do", 1886]
                },
                "JEZYK": ["lat"],
                "LINK": ["http://agadd.home.net.pl/metrykalia/301/sygn.%2072/indeks.htm", ""],
                "INFO": "*na początku księgi karta zawierająca 5 wpisów ślubów z VI-VII 1836 lub 1886 r., s. 1-2; AGAD",
                "MIKROFILM": 73868
        },
        {
                "SYGNATURA": 73,
                "PARAFIA": "Borszczów",
                "DEKANAT": "Borszczów",
                "TYP": "Ekstrakty z księgi metrykalnej",
                "WSAD": {
                        "POSWIADCZENIE": [1854],
                        "FILIACJE": [1853, 1854],
                        "KOICJE": [1853, 1854],
                        "ZGONY": [1853, 1854]
                },
                "JEZYK": ["lat"],
                "LINK": ["http://agadd.home.net.pl/metrykalia/301/sygn.%2073/indeks.htm", ""],
                "INFO": "księga przekazana do AGAD z AP - Przemyśl w 1993 r.",
                "MIKROFILM": 73869
        },
        {
                "SYGNATURA": 74,
                "PARAFIA": "Borszczów",
                "DEKANAT": "Borszczów",
                "TYP": "Księga metrykalna",
                "WSAD": {
                        "FILIACJE": ["od", 1784, "do", 1866],
                        "KOICJE": ["od", 1787, "do", 1893],
                        "ZGONY": ["od", 1785, "do", 1876]
                },
                "JEZYK": ["lat"],
                "LINK": ["http://agadd.home.net.pl/metrykalia/301/sygn.%2074/indeks.htm", ""],
                "INFO": "*Jezierzany - od 1854 r. samodzielna parafia wyodrębniona z par. dek. Borszczów; **w księdze świadectwo ślubu z parafii Jezierzany (4 XI 1883 r.), wyst. 20 XI 1925 r., s. 170; AGAD",
                "MIKROFILM": 73870
        },
        {
                "SYGNATURA": 75,
                "PARAFIA": "Borszczów",
                "DEKANAT": "Borszczów",
                "TYP": "Księga metrykalna",
                "WSAD": {
                        "FILIACJE": ["od", 1784, "do", 1859],
                        "KOICJE": ["od", 1784, "do", 1881],
                        "ZGONY": ["od", 1784, "do", 1877]
                },
                "JEZYK": ["lat",
                        "pol",
                        "ger"
                ],
                "LINK": ["http://agadd.home.net.pl/metrykalia/301/sygn.%2075/indeks.htm", ""],
                "INFO": "*Juriampol - od 1902 r. w par. Korolówka, wyodrębnionej m. in. z par. dek. Borszczów; Nowosiółka Kostiukowa od 1904 r. w par. Szczytowce; na s. 295-346 wpisy śl. z lat 1784-1861 najprawdopodobniej dla wsi Kluwińce, która należała do par. Chorostków; **w księdze list prywatny w sprawie przeprowadzenia poszukiwań genealogicznych potwierdzających szlachectwo, 14 VI 1902, bifolium luzem, s. 311-314, AGAD; (zs)",
                "MIKROFILM": 73871
        },
        {
                "SYGNATURA": 76,
                "PARAFIA": "Borszczów",
                "DEKANAT": "Borszczów",
                "TYP": "Księga metrykalna",
                "WSAD": {
                        "FILIACJE": ["od", 1784, "do", 1837],
                        "KOICJE": ["od", 1785, "do", 1888],
                        "ZGONY": ["od", 1784, "do", 1870]
                },
                "JEZYK": ["lat",
                        "pol",
                        "ger"
                ],
                "LINK": ["http://agadd.home.net.pl/metrykalia/301/sygn.%2076/indeks.htm", ""],
                "INFO": "AGAD",
                "MIKROFILM": 73872
        },
        {
                "SYGNATURA": 77,
                "PARAFIA": "Bóbrka",
                "DEKANAT": "Świrz",
                "TYP": "Księga metrykalna",
                "WSAD": {
                        "FILIACJE": ["od", 1784, "do", 1793]
                },
                "JEZYK": ["lat",
                        "pol",
                        "ger"
                ],
                "LINK": ["http://agadd.home.net.pl/metrykalia/301/sygn.%2077/indeks.htm", ""],
                "INFO": "w księdze znajdują się odrębne wpisy dla miasta Bóbrka i dla każdej wsi wchodzącej w skład parafii - w kolejności podanej w regestrze tytułowym; księga przekazana do AGAD z AP - Przemyśl w 1993 r.",
                "MIKROFILM": 73873
        },
        {
                "SYGNATURA": 78,
                "PARAFIA": "Bóbrka",
                "DEKANAT": "Świrz",
                "TYP": "Księga metrykalna",
                "WSAD": {
                        "FILIACJE": ["od", 1791, "do", 1810]
                },
                "JEZYK": ["lat"],
                "LINK": ["http://agadd.home.net.pl/metrykalia/301/sygn.%2078/indeks.htm", ""],
                "INFO": "*w księdze znajdują się wpisy odrębne (przemieszane w obrębie księgi) dla miasta Bóbrka i dla każdej wsi wchodzącej w skład parafii (Wołowe, Strzałki, Łanki, Ernsdorf, Sarniki) oraz wpisy prowadzone jednocześnie - daty krańcowe tych wpisów są różne; w inwentarzu podano wspólne daty krańcowe dla całej parafii; księga przekazana do AGAD z AP - Przemyśl w 1993 r.; (zs)",
                "MIKROFILM": 73874
        },
        {
                "SYGNATURA": 79,
                "PARAFIA": "Bóbrka",
                "DEKANAT": "Świrz",
                "TYP": "Księga metrykalna",
                "WSAD": {
                        "POSWIADCZENIE": [1831],
                        "FILIACJE": ["od", 1791, "do", 1824, 1831]
                },
                "JEZYK": ["lat",
                        "ger"
                ],
                "LINK": ["http://agadd.home.net.pl/metrykalia/301/sygn.%2079/indeks.htm", ""],
                "INFO": "*patrz - sygn.  78; księga przekazana do AGAD Z AP - Przemyśl w 1993 r.",
                "MIKROFILM": 73875
        },
        {
                "SYGNATURA": 80,
                "PARAFIA": "Bóbrka",
                "DEKANAT": "Świrz",
                "TYP": "Księga metrykalna",
                "WSAD": {
                        "POSWIADCZENIE": [1831],
                        "FILIACJE": ["od", 1824, "do", 1856, 1831]
                },
                "JEZYK": ["lat",
                        "ger"
                ],
                "LINK": ["http://agadd.home.net.pl/metrykalia/301/sygn.%2080/indeks.htm", ""],
                "INFO": "*w księdze znajdują się wpisy odrębne (przemieszane w obrębie księgi) dla miasta Bóbrka i dla każdej wsi wchodzącej w skład parafii (Ernsdorf, Kocurów, Lubeszka, Łanki, Podhorodyszcze, Rehfeld, Romanów, Sarniki, Strzałki, Wołowe); księga przekazana do AGAD Z AP - Przemyśl w 1993 r.; (bzs)",
                "MIKROFILM": 73876
        },
        {
                "SYGNATURA": 81,
                "PARAFIA": "Bóbrka",
                "DEKANAT": "Świrz",
                "TYP": "Księga metrykalna",
                "WSAD": {
                        "POSWIADCZENIE": [1831],
                        "KOICJE": ["od", 1784, "do", 1817, 1831]
                },
                "JEZYK": ["lat",
                        "pol",
                        "ger"
                ],
                "LINK": ["http://agadd.home.net.pl/metrykalia/301/sygn.%2081/indeks.htm", ""],
                "INFO": "wpisy w księdze w kolejności podanej w regestrze tytułowym; księga przekazana do AGAD z AP - Przemyśl w 1993 r.",
                "MIKROFILM": 73877
        },
        {
                "SYGNATURA": 82,
                "PARAFIA": "Bóbrka",
                "DEKANAT": "Świrz",
                "TYP": "Księga metrykalna",
                "WSAD": {
                        "POSWIADCZENIE": [1831],
                        "KOICJE": ["od", 1817, "do", 1826]
                },
                "JEZYK": ["lat",
                        "ger"
                ],
                "LINK": ["http://agadd.home.net.pl/metrykalia/301/sygn.%2082/indeks.htm", ""],
                "INFO": "*wpisy prowadzone jednocześnie dla miasta Bóbrka i poszczególnych wsi; księga przekazana do AGAD z AP - Przemyśl w 1993 r.",
                "MIKROFILM": 73878
        },
        {
                "SYGNATURA": 83,
                "PARAFIA": "Bóbrka",
                "DEKANAT": "Świrz",
                "TYP": "Księga metrykalna",
                "WSAD": {
                        "POSWIADCZENIE": [1831],
                        "ZGONY": ["od", 1784, "do", 1817]
                },
                "JEZYK": ["lat",
                        "pol",
                        "ger"
                ],
                "LINK": ["http://agadd.home.net.pl/metrykalia/301/sygn.%2083/indeks.htm", ""],
                "INFO": "wpisy w kolejności podanej w regestrze tytułowym; na s. 1 wpisy dla niezidentyfikowanej wsi z lat 1794-1797; księga przekazana do AGAD z AP - Przemyśl w 1993 r.",
                "MIKROFILM": 73879
        },
        {
                "SYGNATURA": 84,
                "PARAFIA": "Bóbrka",
                "DEKANAT": "Świrz",
                "TYP": "Księga metrykalna",
                "WSAD": {
                        "ZGONY": ["od", 1817, "do", 1826]
                },
                "JEZYK": ["lat",
                        "ger"
                ],
                "LINK": ["http://agadd.home.net.pl/metrykalia/301/sygn.%2084/indeks.htm", ""],
                "INFO": "*patrz - sygn. 82; księga przekazana do AGAD z AP - Przemyśl w 1993 r.",
                "MIKROFILM": 73880
        },
        {
                "SYGNATURA": 85,
                "PARAFIA": "Bóbrka",
                "DEKANAT": "Świrz",
                "TYP": "Księga metrykalna",
                "WSAD": {
                        "POSWIADCZENIE": [1831],
                        "ZGONY": ["od", 1826, "do", 1857]
                },
                "JEZYK": ["lat",
                        "pol",
                        "ger"
                ],
                "LINK": ["http://agadd.home.net.pl/metrykalia/301/sygn.%2085/indeks.htm", ""],
                "INFO": "w księdze znajdują się wpisy odrębne dla miasta Bóbrka i dla każdej wsi wchodzącej w skład parafii, wpisy dla Bóbrki nie są ciągłe, znajdują się w kilku miejscach księgi; *prawdopodobnie chodzi o wieś Lubeszka; księga przekazana do AGAD z AP - Przemyśl w 1993 r.",
                "MIKROFILM": 73881
        },
        {
                "SYGNATURA": 86,
                "PARAFIA": "Bóbrka",
                "DEKANAT": "Świrz",
                "TYP": "Księga metrykalna",
                "WSAD": {
                        "FILIACJE": ["od", 1744, "do", 1765],
                        "KOICJE": ["od", 1744, "do", 1753]
                },
                "JEZYK": ["lat"],
                "LINK": ["http://agadd.home.net.pl/metrykalia/301/sygn.%2086/indeks.htm", ""],
                "INFO": "wpisy bez rubryk, *na s. 156-167 znajdują się także przemieszane wpisy ur. i śl. z lat 70. i 80 XVIII w.; księga przekazana do AGAD z AP - Przemyśl w 1993 r.",
                "MIKROFILM": 73882
        },
        {
                "SYGNATURA": 87,
                "PARAFIA": "Bóbrka",
                "DEKANAT": "Świrz",
                "TYP": "Ekstrakty z księgi metrykalnej",
                "WSAD": {
                        "POSWIADCZENIE": [1839, 1840, 1842],
                        "FILIACJE": [1835, 1837, 1838, 1839, 184, 1841, 1842],
                        "KOICJE": [1835, 1837, 1838, 1839, 184, 1841, 1842],
                        "ZGONY": [1835, 1837, 1838, 1839, 184, 1841, 1842]
                },
                "JEZYK": ["lat"],
                "LINK": ["http://agadd.home.net.pl/metrykalia/301/sygn.%2087/indeks.htm", ""],
                "INFO": "15 poszytów; akta przekazane do AGAD z AP - Przemyśl w 1993 r.; (zs)",
                "MIKROFILM": 73883
        },
        {
                "SYGNATURA": 88,
                "PARAFIA": "Brody",
                "DEKANAT": "Brody",
                "TYP": "Księga metrykalna",
                "WSAD": {
                        "FILIACJE": ["od", 1707, "do", 1728, "od", 1710, "do", 1712]
                },
                "JEZYK": ["lat"],
                "LINK": ["http://agadd.home.net.pl/metrykalia/301/sygn.%2088/indeks.htm", ""],
                "INFO": "*na końcu księgi dołączona dodatkowa karta zawierająca wpisy małżeństw z lat 1710-1712, s. 125-126; wpisy bez rubryk, niektóre wpisy nieczytelne; księga przekazana do AGAD z AP - Przemyśl w 1993 r.",
                "MIKROFILM": 73884
        },
        {
                "SYGNATURA": 89,
                "PARAFIA": "Brody",
                "DEKANAT": "Brody",
                "TYP": "Księga metrykalna",
                "WSAD": {
                        "FILIACJE": ["od", 1728, "do", 1739]
                },
                "JEZYK": ["lat"],
                "LINK": ["http://agadd.home.net.pl/metrykalia/301/sygn.%2089/indeks.htm", ""],
                "INFO": "wpisy bez rubryk; księga przekazana do AGAD z AP - Przemyśl w 1993 r. (bzs)",
                "MIKROFILM": 73885
        },
        {
                "SYGNATURA": 90,
                "PARAFIA": "Brody",
                "DEKANAT": "Brody",
                "TYP": "Księga metrykalna",
                "WSAD": {
                        "POSWIADCZENIE": [1794],
                        "FILIACJE": ["od", 1776, "do", 1783]
                },
                "JEZYK": ["lat"],
                "LINK": ["http://agadd.home.net.pl/metrykalia/301/sygn.%2090/indeks.htm", ""],
                "INFO": "*wsie Suchodoły, Hołoskowice od 1865 r. należały do par. Ponikwa wyodrębnionej z par. Pieniaki; **Bołdury - później (schematyzmy z XX w.) w par. Leszniów; księga przekazana do AGAD z AP - Przemyśl w 1993 r.",
                "MIKROFILM": 73886
        },
        {
                "SYGNATURA": 91,
                "PARAFIA": "Brody",
                "DEKANAT": "Brody",
                "TYP": "Księga metrykalna",
                "WSAD": {
                        "FILIACJE": ["od", 1783, "do", 1785]
                },
                "JEZYK": ["lat"],
                "LINK": ["http://agadd.home.net.pl/metrykalia/301/sygn.%2091/indeks.htm", ""],
                "INFO": "*patrz - sygn.  90; księga przekazana do AGAD z AP - Przemyśl w 1993 r.",
                "MIKROFILM": 73887
        },
        {
                "SYGNATURA": 92,
                "PARAFIA": "Brody",
                "DEKANAT": "Brody",
                "TYP": "Księga metrykalna",
                "WSAD": {
                        "FILIACJE": ["od", 1785, "do", 1751]
                },
                "JEZYK": ["lat",
                        "pol",
                        "ger"
                ],
                "LINK": ["http://agadd.home.net.pl/metrykalia/301/sygn.%2092/indeks.htm", ""],
                "INFO": "t. III; księga przekazana do AGAD z AP - Przemyśl w 1993 r.",
                "MIKROFILM": 73888
        },
        {
                "SYGNATURA": 93,
                "PARAFIA": "Brody",
                "DEKANAT": "Brody",
                "TYP": "Księga metrykalna",
                "WSAD": {
                        "FILIACJE": ["od", 1784, "do", 1861]
                },
                "JEZYK": ["lat"],
                "LINK": ["http://agadd.home.net.pl/metrykalia/301/sygn.%2093/indeks.htm", ""],
                "INFO": "księga przekazana do AGAD z AP - Przemyśl w 1993 r.",
                "MIKROFILM": 73889
        },
        {
                "SYGNATURA": 94,
                "PARAFIA": "Brody",
                "DEKANAT": "Brody",
                "TYP": "Księga metrykalna",
                "WSAD": {
                        "FILIACJE": ["od", 1785, "do", 1865]
                },
                "JEZYK": ["lat",
                        "pol",
                        "ger"
                ],
                "LINK": ["http://agadd.home.net.pl/metrykalia/301/sygn.%2094/indeks.htm", ""],
                "INFO": "księga przekazana do AGAD z AP - Przemyśl w 1993 r.",
                "MIKROFILM": 73890
        },
        {
                "SYGNATURA": 95,
                "PARAFIA": "Brody",
                "DEKANAT": "Brody",
                "TYP": "Księga metrykalna",
                "WSAD": {
                        "FILIACJE": ["od", 1785, "do", 1846]
                },
                "JEZYK": ["lat",
                        "pol",
                        "ger"
                ],
                "LINK": ["http://agadd.home.net.pl/metrykalia/301/sygn.%2095/indeks.htm", ""],
                "INFO": "t. I; księga przekazana do AGAD z AP - Przemyśl w 1993 r.",
                "MIKROFILM": 73891
        },
        {
                "SYGNATURA": 96,
                "PARAFIA": "Brody",
                "DEKANAT": "Brody",
                "TYP": "Księga metrykalna",
                "WSAD": {
                        "POSWIADCZENIE": [1793],
                        "KOICJE": ["od", 1776, "do", 1783]
                },
                "JEZYK": ["lat",
                        "ger"
                ],
                "LINK": ["http://agadd.home.net.pl/metrykalia/301/sygn.%2096/indeks.htm", ""],
                "INFO": "*(tu także wieś Wysocko), **patrz - sygn.  90; księga przekazana do AGAD z AP - Przemyśl w 1993 r.",
                "MIKROFILM": 73892
        },
        {
                "SYGNATURA": 97,
                "PARAFIA": "Brody",
                "DEKANAT": "Brody",
                "TYP": "Księga metrykalna",
                "WSAD": {
                        "POSWIADCZENIE": [1811],
                        "ZGONY": ["od", 1785, "do", 1805]
                },
                "JEZYK": ["lat"],
                "LINK": ["http://agadd.home.net.pl/metrykalia/301/sygn.%2097/indeks.htm", ""],
                "INFO": "księga przekazana do AGAD z AP - Przemyśl w 1993 r.",
                "MIKROFILM": 73893
        },
        {
                "SYGNATURA": 98,
                "PARAFIA": "Brody",
                "DEKANAT": "Brody",
                "TYP": "Księga metrykalna",
                "WSAD": {
                        "ZGONY": ["od", 1785, "do", 1843]
                },
                "JEZYK": ["lat",
                        "pol",
                        "ger"
                ],
                "LINK": ["http://agadd.home.net.pl/metrykalia/301/sygn.%2098/indeks.htm", ""],
                "INFO": "księga przekazana do AGAD z AP - Przemyśl w 1993 r.",
                "MIKROFILM": 73894
        },
        {
                "SYGNATURA": 99,
                "PARAFIA": "Brody",
                "DEKANAT": "Brody",
                "TYP": "Księga metrykalna",
                "WSAD": {
                        "ZGONY": ["od", 1785, "do", 1864]
                },
                "JEZYK": ["lat",
                        "pol",
                        "ger"
                ],
                "LINK": ["http://agadd.home.net.pl/metrykalia/301/sygn.%2099/indeks.htm", ""],
                "INFO": "t. I; księga przekazana do AGAD z AP - Przemyśl w 1993 r.",
                "MIKROFILM": 73895
        },
        {
                "SYGNATURA": 100,
                "PARAFIA": "Brody",
                "DEKANAT": "Brody",
                "TYP": "Księga metrykalna",
                "WSAD": {
                        "FILIACJE": ["od", 1747, "do", 1763],
                        "KOICJE": ["od", 1748, "do", 1763]
                },
                "JEZYK": ["lat"],
                "LINK": ["http://agadd.home.net.pl/metrykalia/301/sygn.%20100/indeks.htm", ""],
                "INFO": "wpisy bez rubryk; księga prowadzona dwustronnie; przekazana do AGAD z AP - Przemyśl w 1993 r.",
                "MIKROFILM": 73896
        }, {
                "SYGNATURA": 1948,
                "PARAFIA": "Lwów, św.Marii Magdaleny",
                "DEKANAT": "Lwów",
                "TYP": "Księga metrykalna",
                "WSAD": {
                        "FILIACJE": ["od", 1909, "do", 1914],
                        "KOICJE": ["od", 1909, "do", 1914],
                        "ZGONY": ["od", 1909, "do", 1914]
                },
                "JEZYK": ["lat", "rus"],
                "LINK": ["http://agadd2.home.net.pl/metrykalia/301/sygn.%201948/indeks.htm", ""],
                "INFO": "kopie; wpisy z l. 1910-1914  w kolejności: śl., ur., zg.; w księdze dopiski USC z okresu późniejszego"
        }, {
                "SYGNATURA": 1949,
                "PARAFIA": "Lwów, św.Elżbiety",
                "DEKANAT": "Lwów",
                "TYP": "Księga metrykalna",
                "WSAD": {
                        "FILIACJE": ["od", 1911, "do", 1914],
                        "KOICJE": ["od", 1911, "do", 1914],
                        "ZGONY": ["od", 1911, "do", 1914]
                },
                "JEZYK": ["lat"],
                "LINK": ["http://agadd2.home.net.pl/metrykalia/301/sygn.%201949/indeks.htm", ""],
                "INFO": "kopie; z 1911 r. tylko wpisy ur. i zg.; w księdze dopiski USC z okresu późniejszego"
        }, {
                "SYGNATURA": 1950,
                "PARAFIA": "Mikulińce/Ładyczyn*",
                "DEKANAT": "Trembowla",
                "TYP": "Księga metrykalna",
                "WSAD": {
                        "ZGONY": ["od", 1846, "do", 1914]
                },
                "JEZYK": ["lat"],
                "LINK": ["http://agadd2.home.net.pl/metrykalia/301/sygn.%201950/indeks.htm", ""],
                "INFO": "*parafia Ładyczyn wyodrębniona w 1911 r. z par. Mikulińce z wsią Ludwikówka"
        }, {
                "SYGNATURA": 1951,
                "PARAFIA": "Skała",
                "DEKANAT": "Jazłowiec",
                "TYP": "Księga metrykalna",
                "WSAD": {
                        "FILIACJE": ["od", 1887, "do", 1897, 1899, 1900],
                        "KOICJE": ["od", 1887, "do", 1897, 1899, 1900],
                        "ZGONY": ["od", 1887, "do", 1897, 1899, 1900]
                },
                "JEZYK": ["lat"],
                "LINK": ["http://agadd2.home.net.pl/metrykalia/301/sygn.%201951/indeks.htm", ""],
                "INFO": "*parafia Łosiacz wyodrębniona z par. Skała w 1909 r., z wsiami: Bosyry, Dębówka, Kociubińczyki, Siekierzyńce; ** parafia Turylcze wyodrębniona z par. Skała w 1901 r. z wsiami: Podfilipie, Pukłaki, Słobódka, Wierzbówka; brak rocznika 1898"
        }, {
                "SYGNATURA": 1952,
                "TYP": "Księga metrykalna",
                "WSAD": {
                        "FILIACJE": ["od", 1909, "do", 1914],
                        "KOICJE": ["od", 1909, "do", 1914],
                        "ZGONY": ["od", 1909, "do", 1914]
                },
                "JEZYK": ["lat"],
                "LINK": ["http://agadd2.home.net.pl/metrykalia/301/sygn.%201952/indeks.htm", ""],
                "INFO": "z 1909 r. - tylko wpisy ur. i śl.; *w seriach  z lat 1909-1910 także wpisy dla wsi Dołżanka, która wg schematyzmów kościelnych z tego okresu należała do par. Zabojki, wyodrębnionej w 1904 r. z par. Kozłów, dek. Buczacz"
        }, {
                "SYGNATURA": 1953,
                "PARAFIA": "Zimna Woda",
                "DEKANAT": "Gródek Jagielloński",
                "TYP": "Księga metrykalna",
                "WSAD": {
                        "ZGONY": ["od", 1780, "do", 1913]
                },
                "JEZYK": ["lat"],
                "LINK": ["http://agadd2.home.net.pl/metrykalia/301/sygn.%201953/indeks.htm", ""]
        }, {
                "SYGNATURA": 1954,
                "PARAFIA": "Baworów",
                "DEKANAT": "Tarnopol",
                "TYP": "Księga metrykalna",
                "WSAD": {
                        "FILIACJE": ["od", 1869, "do", 1915]
                },
                "JEZYK": ["lat", "ger"],
                "LINK": ["http://agadd2.home.net.pl/metrykalia/301/sygn.%201954/indeks.htm", ""]
        }, {
                "SYGNATURA": 1955,
                "PARAFIA": "Chocimierz",
                "DEKANAT": "Horodenka",
                "TYP": "Księga metrykalna",
                "WSAD": {
                        "KOICJE": ["od", 1880, "do", 1915]
                },
                "JEZYK": ["lat"],
                "LINK": ["http://agadd2.home.net.pl/metrykalia/301/sygn.%201955/indeks.htm", ""]
        }, {
                "SYGNATURA": 1956,
                "PARAFIA": "Kołomyja",
                "DEKANAT": "Kołomyja",
                "TYP": "Wojskowa Księga metrykalna",
                "WSAD": {
                        "ZGONY": ["od", 1871, "do", 1915]
                },
                "JEZYK": ["ger"],
                "LINK": ["http://agadd2.home.net.pl/metrykalia/301/sygn.%201956/indeks.htm", ""],
                "INFO": "wpisy od s. 2; s. 1 nie zapisana; z 1871 r. - 1 wpis"
        }
]
